MANIFEST.in
README.rst
ez_setup.py
rc_setup.py
setup.py
vlc_ctrl/__init__.py
vlc_ctrl/__main__.py
vlc_ctrl/client.py
vlc_ctrl/filter.py
vlc_ctrl/main.py
vlc_ctrl/player.py
vlc_ctrl/player_list.py
vlc_ctrl/version.py
vlc_ctrl.egg-info/PKG-INFO
vlc_ctrl.egg-info/SOURCES.txt
vlc_ctrl.egg-info/dependency_links.txt
vlc_ctrl.egg-info/entry_points.txt
vlc_ctrl.egg-info/requires.txt
vlc_ctrl.egg-info/top_level.txt